eastern/__init__.py
eastern/__main__.py
eastern/cli.py
eastern/formatter.py
eastern/job_manager.py
eastern/kubectl.py
eastern/kubeyml_helper.py
eastern/plugin.py
eastern/timeout.py
eastern/yaml_formatter/__init__.py
eastern/yaml_formatter/formatter.py
eastern/yaml_formatter/overrides.py
eastern/yaml_formatter/utils.py
eastern-5.0.0.dist-info/LICENSE
eastern-5.0.0.dist-info/METADATA
eastern-5.0.0.dist-info/WHEEL
eastern-5.0.0.dist-info/entry_points.txt
eastern-5.0.0.dist-info/top_level.txt
eastern-5.0.0.dist-info/RECORD
