Metadata-Version: 2.1
Name: eastern
Version: 5.0.0
Summary: Simple Kubernetes Deployment
Home-page: https://github.com/wongnai/eastern
License: MIT
Platform: UNKNOWN
Classifier: Development Status :: 5 - Production/Stable
Classifier: Intended Audience :: System Administrators
Classifier: License :: OSI Approved :: MIT License
Classifier: Programming Language :: Python :: 3 :: Only
Classifier: Topic :: System :: Systems Administration
Requires-Python: >=3.9
License-File: LICENSE
Requires-Dist: Click (~=6.7)
Requires-Dist: click-log (~=0.3.2)
Requires-Dist: PyYAML (~=6.0)
Requires-Dist: stevedore (~=1.29.0)
